{
  "firstLayout": "",
  "gdVersion": {
    "build": 99,
    "major": 4,
    "minor": 0,
    "revision": 0
  },
  "properties": {
    "adaptGameResolutionAtRuntime": true,
    "folderProject": true,
    "orientation": "landscape",
    "packageName": "com.example.gamename",
    "pixelsRounding": false,
    "projectUuid": "5bc7e4bc-b9f9-4196-92c3-69305f82ca25",
    "scaleMode": "linear",
    "sizeOnStartupMode": "adaptWidth",
    "templateSlug": "",
    "useExternalSourceFiles": false,
    "version": "1.0.0",
    "name": "Sustainability Adventure Game",
    "description": "",
    "author": "",
    "windowWidth": 800,
    "windowHeight": 600,
    "latestCompilationDirectory": "",
    "maxFPS": 60,
    "minFPS": 20,
    "verticalSync": false,
    "platformSpecificAssets": {},
    "loadingScreen": {
      "backgroundColor": 0,
      "backgroundFadeInDuration": 0.2,
      "backgroundImageResourceName": "",
      "gdevelopLogoStyle": "light",
      "logoAndProgressFadeInDuration": 0.2,
      "logoAndProgressLogoFadeInDelay": 0.2,
      "minDuration": 1.5,
      "progressBarColor": 16777215,
      "progressBarHeight": 20,
      "progressBarMaxWidth": 200,
      "progressBarMinWidth": 40,
      "progressBarWidthPercent": 30,
      "showGDevelopSplash": false,
      "showProgressBar": false
    },
    "authorIds": [],
    "categories": [],
    "playableDevices": [],
    "extensionProperties": [],
    "platforms": [
      {
        "name": "GDevelop JS platform"
      }
    ],
    "currentPlatform": "GDevelop JS platform"
  },
  "resources": {
    "resources": [],
    "resourceFolders": []
  },
  "objects": [],
  "objectsGroups": [],
  "variables": [],
  "layouts": [
    {
      "__REFERENCE_TO_SPLIT_OBJECT": true,
      "referenceTo": "/layouts/title-screen"
    }
  ],
  "externalEvents": [],
  "eventsFunctionsExtensions": [
    {
      "__REFERENCE_TO_SPLIT_OBJECT": true,
      "referenceTo": "/eventsFunctionsExtensions/panelspritebutton"
    }
  ],
  "externalLayouts": [],
  "externalSourceFiles": []
}